fontpreview/__init__.py
fontpreview/fontbanner.py
fontpreview/fontpage.py
fontpreview/fontpreview.py
fontpreview-0.9.0.dist-info/LICENSE.md
fontpreview-0.9.0.dist-info/METADATA
fontpreview-0.9.0.dist-info/WHEEL
fontpreview-0.9.0.dist-info/top_level.txt
fontpreview-0.9.0.dist-info/RECORD
