Metadata-Version: 2.1
Name: fontpreview
Version: 0.9.0
Summary: Python library for font previews
Home-page: https://github.com/matteoguadrini/fontpreview
Author: Matteo Guadrini
Author-email: matteo.guadrini@hotmail.it
Maintainer: Matteo Guadrini
Maintainer-email: matteo.guadrini@hotmail.it
License: GNU General Public License v3.0
Keywords: fontpreview library font previews
Platform: UNKNOWN
Classifier: Programming Language :: Python :: 3
Classifier: License :: OSI Approved :: GNU General Public License v3 (GPLv3)
Classifier: Operating System :: OS Independent
Requires-Python: >=3.6
Requires-Dist: Pillow
